readme_renderer/__about__.py
readme_renderer/__init__.py
readme_renderer/__main__.py
readme_renderer/clean.py
readme_renderer/markdown.py
readme_renderer/py.typed
readme_renderer/rst.py
readme_renderer/txt.py
readme_renderer-41.0.dist-info/LICENSE
readme_renderer-41.0.dist-info/METADATA
readme_renderer-41.0.dist-info/WHEEL
readme_renderer-41.0.dist-info/top_level.txt
readme_renderer-41.0.dist-info/RECORD
